pn2utl/_C.cpython-310-x86_64-linux-gnu.so
pn2utl/__init__.py
pn2utl/aggregation.py
pn2utl/attention.py
pn2utl/grouping.py
pn2utl/interpolation.py
pn2utl/query.py
pn2utl/sampling.py
pn2utl/subtraction.py
pn2utl/utils.py
pn2utl-0.1.2.dist-info/METADATA
pn2utl-0.1.2.dist-info/WHEEL
pn2utl-0.1.2.dist-info/top_level.txt
pn2utl-0.1.2.dist-info/RECORD
