Metadata-Version: 2.1
Name: pn2utl
Version: 0.1.2
Summary: test first package
Home-page: https://gitee.com/leehiking/my_pkg_1
Author: leehiking
Author-email: gz6201347@163.com
Classifier: Programming Language :: Python :: 3
Classifier: License :: OSI Approved :: MIT License
Classifier: Operating System :: OS Independent
Requires-Python: >=3.0
Requires-Dist: torch (>=1.0)
Requires-Dist: numpy (>=1.0)
